ruddr/__init__.py
ruddr/__main__.py
ruddr/addrfile.py
ruddr/configuration.py
ruddr/exceptions.py
ruddr/main.py
ruddr/manager.py
ruddr/notifiers/__init__.py
ruddr/notifiers/iface.py
ruddr/notifiers/notifier.py
ruddr/notifiers/static.py
ruddr/notifiers/systemd.py
ruddr/notifiers/web.py
ruddr/updaters/__init__.py
ruddr/updaters/duckdns.py
ruddr/updaters/freedns.py
ruddr/updaters/gandi.py
ruddr/updaters/he.py
ruddr/updaters/standard.py
ruddr/updaters/updater.py
ruddr/util/__init__.py
ruddr/util/getifaceaddrs.py
ruddr/util/restrictfamily.py
ruddr/util/sdnotify.py
ruddr/util/zones.py
ruddr-0.0.1a4.dist-info/METADATA
ruddr-0.0.1a4.dist-info/WHEEL
ruddr-0.0.1a4.dist-info/entry_points.txt
ruddr-0.0.1a4.dist-info/top_level.txt
ruddr-0.0.1a4.dist-info/RECORD
