Metadata-Version: 2.1
Name: ruddr
Version: 0.0.1a4
Summary: Robotic Updater for Dynamic DNS Records
Author: Dominick C. Pastore
Author-email: ruddr@dcpx.org
License: GNU GENERAL PUBLIC LICENSE
Project-URL: Homepage, https://ruddr.dcpx.org/
Project-URL: Documentation, https://ruddr.dcpx.org/
Project-URL: Repository, https://github.com/dominickpastore/ruddr/
Project-URL: Changelog, https://github.com/dominickpastore/ruddr/blob/master/CHANGELOG.md
Project-URL: Bug Tracker, https://github.com/dominickpastore/ruddr/issues
Project-URL: Discussion, https://github.com/dominickpastore/ruddr/discussions
Classifier: Environment :: No Input/Output (Daemon)
Classifier: Intended Audience :: Developers
Classifier: Intended Audience :: Information Technology
Classifier: Intended Audience :: System Administrators
Classifier: Intended Audience :: Telecommunications Industry
Classifier: License :: OSI Approved :: GNU General Public License v3 or later (GPLv3+)
Classifier: Operating System :: POSIX
Classifier: Operating System :: POSIX :: Linux
Classifier: Programming Language :: Python :: 3
Classifier: Programming Language :: Python :: 3 :: Only
Classifier: Topic :: Internet
Classifier: Topic :: Internet :: Name Service (DNS)
Classifier: Topic :: System :: Networking
Classifier: Topic :: System :: Systems Administration
Classifier: Topic :: Utilities
Classifier: Typing :: Typed
Requires-Python: >=3.7
Requires-Dist: requests
Requires-Dist: netifaces (>=0.11.0)
Requires-Dist: dnspython (~=2.0)
Requires-Dist: tldextract (~=3.0)
Requires-Dist: importlib-metadata ; python_version < "3.10"
Requires-Dist: typing-extensions (~=4.0) ; python_version < "3.8"
Provides-Extra: dev
Requires-Dist: ruddr[docs,test] ; extra == 'dev'
Provides-Extra: docs
Requires-Dist: sphinx ; extra == 'docs'
Provides-Extra: staticanalysis
Requires-Dist: flake8 (>=5) ; extra == 'staticanalysis'
Requires-Dist: pytype (>=2023.01.10) ; extra == 'staticanalysis'
Provides-Extra: systemd
Requires-Dist: PyGObject ; extra == 'systemd'
Provides-Extra: test
Requires-Dist: ruddr[staticanalysis,unittest] ; extra == 'test'
Requires-Dist: pytest-cov ; extra == 'test'
Requires-Dist: tox (>=4) ; extra == 'test'
Provides-Extra: unittest
Requires-Dist: pytest (>=6) ; extra == 'unittest'
Requires-Dist: pytest-mock ; extra == 'unittest'
Requires-Dist: coverage[toml] ; extra == 'unittest'
